djaodjin_signup-0.11.1.dist-info/licenses/LICENSE.txt
signup/__init__.py
signup/auth.py
signup/authentication.py
signup/compat.py
signup/decorators.py
signup/docs.py
signup/filters.py
signup/forms.py
signup/helpers.py
signup/middleware.py
signup/mixins.py
signup/models.py
signup/serializers.py
signup/serializers_overrides.py
signup/settings.py
signup/signals.py
signup/tests.py
signup/utils.py
signup/validators.py
signup/api/__init__.py
signup/api/activities.py
signup/api/auth.py
signup/api/contacts.py
signup/api/keys.py
signup/api/tokens.py
signup/api/users.py
signup/backends/__init__.py
signup/backends/auth.py
signup/backends/auth_ldap.py
signup/backends/base.py
signup/backends/sts_credentials.py
signup/backends/email_verification/__init__.py
signup/backends/email_verification/base.py
signup/backends/phone_verification/__init__.py
signup/backends/phone_verification/aws_sns.py
signup/backends/phone_verification/base.py
signup/backends/phone_verification/fake.py
signup/migrations/0001_v0_1_9.py
signup/migrations/0002_0_2_0.py
signup/migrations/0003_0_2_1.py
signup/migrations/0004_0_2_6.py
signup/migrations/0005_0_2_8.py
signup/migrations/0006_v0_4_7.py
signup/migrations/0007_v0_4_8.py
signup/migrations/0008_v0_6_0.py
signup/migrations/0009_v0_8_0.py
signup/migrations/0010_v0_9_0.py
signup/migrations/0011_auto_20231006_1747.py
signup/migrations/0012_v0_10_0.py
signup/migrations/__init__.py
signup/static/js/djaodjin-password-strength.js
signup/static/js/djaodjin-resources-vue.js
signup/static/js/djaodjin-resources.js
signup/static/js/djaodjin-signup-vue.js
signup/templates/activities/accounts/account.html
signup/templates/activities/accounts/base.html
signup/templates/activities/accounts/index.html
signup/templates/activities/contacts/base.html
signup/templates/activities/contacts/contact.html
signup/templates/activities/contacts/index.html
signup/templates/login/disabled.html
signup/templates/login/index.html
signup/templates/login/verification_key.html
signup/templates/notification/password_reset.eml
djaodjin_signup-0.11.1.dist-info/METADATA
djaodjin_signup-0.11.1.dist-info/WHEEL
djaodjin_signup-0.11.1.dist-info/top_level.txt
djaodjin_signup-0.11.1.dist-info/RECORD
