Metadata-Version: 2.4
Name: djaodjin-signup
Version: 0.11.1
Summary: Django app for user authentication
Author-email: The DjaoDjin Team <help@djaodjin.com>
Maintainer-email: The DjaoDjin Team <help@djaodjin.com>
License: BSD-2-Clause
Project-URL: repository, https://github.com/djaodjin/djaodjin-signup
Project-URL: documentation, https://djaodjin-signup.readthedocs.io/
Project-URL: changelog, https://github.com/djaodjin/djaodjin-signup/changelog
Keywords: signup,authentication,frictionless,2fa,mfa,otp,oauth,saml
Classifier: Framework :: Django
Classifier: Environment :: Web Environment
Classifier: Programming Language :: Python
Classifier: License :: OSI Approved :: BSD License
Requires-Python: >=3.7
License-File: LICENSE.txt
Requires-Dist: boto3>=1.4.4
Requires-Dist: Django>=1.11
Requires-Dist: django-fernet-fields>=0.6
Requires-Dist: django-phonenumber-field>=2.4.0
Requires-Dist: django-recaptcha>=2.0
Requires-Dist: djangorestframework>=3.9
Requires-Dist: phonenumbers>=8.12.6
Requires-Dist: PyJWT>=1.6.1
Requires-Dist: pyotp>=2.8.0
Requires-Dist: python3-saml>=1.2.1
Requires-Dist: social-auth-app-django>=4.0.0
Requires-Dist: social-auth-core>=4.2.0
Provides-Extra: ldap
Requires-Dist: python-ldap>=3.2.0; extra == "ldap"
Dynamic: license-file
